keycap_designer/.gitignore
keycap_designer/__init__.py
keycap_designer/__main__.py
keycap_designer/_version.py
keycap_designer/color_management.py
keycap_designer/constants.py
keycap_designer/image.py
keycap_designer/manuscript.py
keycap_designer/overwrite_reportlab.py
keycap_designer/preview.py
keycap_designer/area/junana/15u-convex-front.png
keycap_designer/area/junana/15u-convex-tf.png
keycap_designer/area/junana/15u-convex-top.png
keycap_designer/area/junana/15u-front.png
keycap_designer/area/junana/15u-tf.png
keycap_designer/area/junana/15u-top.png
keycap_designer/area/junana/15u.png
keycap_designer/area/junana/1u-convex-front.png
keycap_designer/area/junana/1u-convex-tf.png
keycap_designer/area/junana/1u-convex-top.png
keycap_designer/area/junana/1u-front.png
keycap_designer/area/junana/1u-tf.png
keycap_designer/area/junana/1u-top.png
keycap_designer/area/junana/1u.png
keycap_designer/area/junana/225u-convex-front.png
keycap_designer/area/junana/225u-convex-tf.png
keycap_designer/area/junana/225u-convex-top.png
keycap_designer/area/junana/225u-front.png
keycap_designer/area/junana/225u-tf.png
keycap_designer/area/junana/225u-top.png
keycap_designer/area/junana/225u.png
keycap_designer/area/junana/note.txt
keycap_designer/area/xda/125u.png
keycap_designer/area/xda/15u.png
keycap_designer/area/xda/175u.png
keycap_designer/area/xda/1u-front.png
keycap_designer/area/xda/1u.png
keycap_designer/area/xda/225u.png
keycap_designer/area/xda/275u.png
keycap_designer/area/xda/2u.png
keycap_designer/deform/__init__.py
keycap_designer/deform/deform_test.py
keycap_designer/deform/junana/__init__.py
keycap_designer/deform/junana/f15u.py
keycap_designer/deform/junana/f15u_convex.py
keycap_designer/deform/junana/f1u.py
keycap_designer/deform/junana/f1u_convex.py
keycap_designer/deform/junana/f225u.py
keycap_designer/deform/junana/f225u_convex.py
keycap_designer/deform/junana/area/f15u.png
keycap_designer/deform/junana/area/f15u_convex.png
keycap_designer-0.1.6.dist-info/licenses/LICENSE
keycap_designer-0.1.6.dist-info/METADATA
keycap_designer-0.1.6.dist-info/WHEEL
keycap_designer-0.1.6.dist-info/entry_points.txt
keycap_designer-0.1.6.dist-info/top_level.txt
keycap_designer-0.1.6.dist-info/RECORD
