Metadata-Version: 2.4
Name: keycap-designer
Version: 0.1.6
Summary: Keycap Designer for DecentKeyboards' Custom Keycaps
License-Expression: MIT
Project-URL: Repository, https://github.com/hajimen/keycap_designer
Classifier: Development Status :: 3 - Alpha
Classifier: Environment :: Console
Classifier: Intended Audience :: Developers
Classifier: Operating System :: MacOS :: MacOS X
Classifier: Operating System :: Microsoft :: Windows
Classifier: Programming Language :: Python
Requires-Python: >=3.11
License-File: LICENSE
Requires-Dist: pillow==11.3.0
Requires-Dist: opencv-python==4.11.0.86
Requires-Dist: frozendict==2.4.6
Requires-Dist: reportlab==4.4.2
Requires-Dist: cmm-16bit==0.1.6
Requires-Dist: ordered_enum==0.0.9
Requires-Dist: prompt_toolkit==3.0.51
Requires-Dist: pykle_serial==0.1.1
Requires-Dist: scikit-image==0.26.0
Requires-Dist: safetensors==0.5.3
Requires-Dist: pikepdf==9.11.0
Requires-Dist: mslex==1.3.0
Provides-Extra: test
Requires-Dist: pdf2image; extra == "test"
Dynamic: license-file
